CHANGES.md
MANIFEST.in
README.md
setup.py
pmongo/__init__.py
pmongo/document.py
pmongo/query.py
pmongo/utils.py
pmongo.egg-info/PKG-INFO
pmongo.egg-info/SOURCES.txt
pmongo.egg-info/dependency_links.txt
pmongo.egg-info/not-zip-safe
pmongo.egg-info/requires.txt
pmongo.egg-info/top_level.txt