Metadata-Version: 1.0
Name: pmongo
Version: 1.0.14
Summary: A small Python MongoDB Document-Based access engine.
Home-page: https://github.com/sintrb/pmongo/
Author: trb
Author-email: sintrb@gmail.com
License: UNKNOWN
Keywords: mongo,django,orm,nosql
Platform: UNKNOWN
